imperial/__init__.py
imperial/document.py
imperial/exceptions.py
imperial/imperialbin.py
imperial/checks/__init__.py
imperial/checks/ensure_api_token.py
imperial/checks/ensure_content.py
imperial/checks/ensure_document_id.py
imperial/client/__init__.py
imperial/client/body.py
imperial/client/check_api_token.py
imperial/client/create_document.py
imperial/client/delete_document.py
imperial/client/edit_document.py
imperial/client/get_document.py
imperial/client/purge_documents.py
imperial/client/request.py
imperial/tests/__init__.py
imperial/tests/mock.py
imperial/tests/response_creator.py
imperial/tests/test_create_document.py
imperial/tests/test_document.py
imperial/tests/test_exceptions.py
imperial/tests/test_get_document.py
imperial/tests/test_json_parser.py
imperial/utils/__init__.py
imperial/utils/hostname.py
imperial/utils/parser.py
imperial.py-2.0.1.dist-info/LICENSE
imperial.py-2.0.1.dist-info/METADATA
imperial.py-2.0.1.dist-info/WHEEL
imperial.py-2.0.1.dist-info/top_level.txt
imperial.py-2.0.1.dist-info/RECORD
