Metadata-Version: 2.1
Name: imperial.py
Version: 2.0.1
Summary: ImperialBin is a hastebin alternative built with UI and user experience in mind.
Home-page: https://github.com/imperialbin/imperial-py
Author: Hexiro
Author-email: realhexiro@gmail.com
License: MPL2
Keywords: py,py3,python,python3,imperialbin,hastebin,pastebin
Platform: UNKNOWN
Classifier: Environment :: Console
Classifier: Intended Audience :: Developers
Classifier: Natural Language :: English
Classifier: License :: OSI Approved :: Mozilla Public License 2.0 (MPL 2.0)
Classifier: Programming Language :: Python :: 3 :: Only
Classifier: Programming Language :: Python
Classifier: Topic :: Software Development
Requires-Python: >=3.6
Requires-Dist: requests
